django_shortcodes-0.4.0.dist-info/METADATA
django_shortcodes-0.4.0.dist-info/top_level.txt
django_shortcodes-0.4.0.dist-info/WHEEL
django_shortcodes-0.4.0.dist-info/metadata.json
django_shortcodes-0.4.0.dist-info/RECORD
django_shortcodes-0.4.0.dist-info/DESCRIPTION.rst
shortcodes/parser.py
shortcodes/__init__.py
shortcodes/templatetags/shortcodes_filters.py
shortcodes/templatetags/__init__.py
shortcodes/parsers/vimeo.py
shortcodes/parsers/__init__.py
shortcodes/parsers/youtube.py
shortcodes/templates/shortcodes/vimeo.html
