Metadata-Version: 2.0
Name: django-shortcodes
Version: 0.4.0
Summary: WordPress shortcode support for Django
Home-page: https://github.com/martey/django-shortcodes
Author: Martey Dodoo
Author-email: django-shortcodes@marteydodoo.com
License: MIT
Platform: UNKNOWN
Classifier: Development Status :: 5 - Production/Stable
Classifier: Framework :: Django
Classifier: Intended Audience :: Developers
Classifier: License :: OSI Approved :: MIT License
